{
  "name": "Reviews",
  "base": "PersistedModel",
  "idInjection": true,
  "options": {
    "validateUpsert": true
  },
  "properties": {
    "name": {
      "type": "string",
      "required": true
    },
    "rating": {
      "type": "number",
      "required": true
    },
    "comments": {
      "type": "string"
    },
    "restaurantId": {
      "type": "string",
      "required": true
    },
    "userId": {
      "type": "string",
      "required": true
    },
    "date": {
      "type": "date",
      "defaultFn": "now"
    }
  },
  "validations": [],
  "relations": {},
  "acls": [
    {
      "accessType": "*",
      "principalType": "ROLE",
      "principalId": "$everyone",
      "permission": "DENY"
    },
    {
      "accessType": "READ",
      "principalType": "ROLE",
      "principalId": "$everyone",
      "permission": "ALLOW"
    },
    {
      "accessType": "WRITE",
      "principalType": "ROLE",
      "principalId": "$authenticated",
      "permission": "ALLOW"
    }
  ],
  "methods": {}
}
